dataframe_with_button/__init__.py
dataframe_with_button/example2.py
dataframe_with_button/frontend/build/asset-manifest.json
dataframe_with_button/frontend/build/bootstrap.min.css
dataframe_with_button/frontend/build/index.html
dataframe_with_button/frontend/build/static/js/main.29552f14.js
dataframe_with_button/frontend/build/static/js/main.29552f14.js.LICENSE.txt
dataframe_with_button/frontend/build/static/js/main.29552f14.js.map
dataframe_with_button-0.0.2.dist-info/LICENSE
dataframe_with_button-0.0.2.dist-info/METADATA
dataframe_with_button-0.0.2.dist-info/WHEEL
dataframe_with_button-0.0.2.dist-info/top_level.txt
dataframe_with_button-0.0.2.dist-info/RECORD
